profanity_protector/__init__.py
profanity_protector/profanity_protector.py
profanity_protector/data/model.joblib
profanity_protector/data/sentence-transformers_all-MiniLM-L6-v2/.gitattributes
profanity_protector/data/sentence-transformers_all-MiniLM-L6-v2/README.md
profanity_protector/data/sentence-transformers_all-MiniLM-L6-v2/config.json
profanity_protector/data/sentence-transformers_all-MiniLM-L6-v2/config_sentence_transformers.json
profanity_protector/data/sentence-transformers_all-MiniLM-L6-v2/data_config.json
profanity_protector/data/sentence-transformers_all-MiniLM-L6-v2/modules.json
profanity_protector/data/sentence-transformers_all-MiniLM-L6-v2/pytorch_model.bin
profanity_protector/data/sentence-transformers_all-MiniLM-L6-v2/sentence_bert_config.json
profanity_protector/data/sentence-transformers_all-MiniLM-L6-v2/special_tokens_map.json
profanity_protector/data/sentence-transformers_all-MiniLM-L6-v2/tokenizer.json
profanity_protector/data/sentence-transformers_all-MiniLM-L6-v2/tokenizer_config.json
profanity_protector/data/sentence-transformers_all-MiniLM-L6-v2/train_script.py
profanity_protector/data/sentence-transformers_all-MiniLM-L6-v2/vocab.txt
profanity_protector/data/sentence-transformers_all-MiniLM-L6-v2/1_Pooling/config.json
tests/__init__.py
tests/test_profanity_check.py
profanity_protector-1.0.0.dist-info/LICENSE
profanity_protector-1.0.0.dist-info/METADATA
profanity_protector-1.0.0.dist-info/WHEEL
profanity_protector-1.0.0.dist-info/top_level.txt
profanity_protector-1.0.0.dist-info/RECORD
