Metadata-Version: 2.1
Name: profanity-protector
Version: 1.0.0
Summary: An even more robust fork of 'profanity-check'.
Home-page: https://github.com/DanielWeidinger/profanity-protector
Author: Daniel Weidinger
Author-email: daniel.weidinger@codl.at
Classifier: Development Status :: 5 - Production/Stable
Classifier: Natural Language :: English
Classifier: Programming Language :: Python :: 3
Classifier: License :: OSI Approved :: MIT License
Classifier: Operating System :: OS Independent
License-File: LICENSE
Requires-Dist: joblib (>=0.14.1)
Requires-Dist: scikit-learn (>=0.20.2)
Requires-Dist: sentence-transformers (==2.2.2)
